hanzo_tools/__init__.py
hanzo_tools/memory/__init__.py
hanzo_tools/memory/knowledge_tools.py
hanzo_tools/memory/memory_tools.py
hanzo_tools_memory-0.2.0.dist-info/METADATA
hanzo_tools_memory-0.2.0.dist-info/WHEEL
hanzo_tools_memory-0.2.0.dist-info/entry_points.txt
hanzo_tools_memory-0.2.0.dist-info/top_level.txt
hanzo_tools_memory-0.2.0.dist-info/RECORD
